rosbag_topic_remove/__init__.py
rosbag_topic_remove/__main__.py
rosbag_topic_remove/topic_remover.py
rosbag_topic_remove/utils.py
rosbag_topic_remove-0.0.2.dist-info/entry_points.txt
rosbag_topic_remove-0.0.2.dist-info/LICENSE
rosbag_topic_remove-0.0.2.dist-info/WHEEL
rosbag_topic_remove-0.0.2.dist-info/METADATA
rosbag_topic_remove-0.0.2.dist-info/RECORD
