Metadata-Version: 2.1
Name: rosbag-topic-remove
Version: 0.0.2
Summary: Remove topics from rosbags
Author-email: damienlarocque <phicoltan@gmail.com>
Requires-Python: >=3.9
Classifier: License :: OSI Approved :: MIT License
Classifier: Programming Language :: Python :: 3
Classifier: Programming Language :: Python :: 3.9
Requires-Dist: rosbags
Requires-Dist: tqdm
Requires-Dist: black ; extra == "dev"
Requires-Dist: pylint ; extra == "dev"
Requires-Dist: bump2version ; extra == "dev"
Project-URL: Homepage, https://github.com/IamPhytan/rosbag-topic-remove
Project-URL: Repository on GitHub, https://github.com/IamPhytan/rosbag-topic-remove
Project-URL: Repository on GitLab, https://gitlab.com/damienlarocque/rosbag-topic-remove
Provides-Extra: dev
